HISTORY.txt
LICENSE.txt
MANIFEST.in
README.txt
setup.py
src/inqbus/__init__.py
src/inqbus.ocf.generic.egg-info/PKG-INFO
src/inqbus.ocf.generic.egg-info/SOURCES.txt
src/inqbus.ocf.generic.egg-info/dependency_links.txt
src/inqbus.ocf.generic.egg-info/entry_points.txt
src/inqbus.ocf.generic.egg-info/namespace_packages.txt
src/inqbus.ocf.generic.egg-info/not-zip-safe
src/inqbus.ocf.generic.egg-info/requires.txt
src/inqbus.ocf.generic.egg-info/top_level.txt
src/inqbus/ocf/__init__.py
src/inqbus/ocf/generic/__init__.py
src/inqbus/ocf/generic/agent.py
src/inqbus/ocf/generic/container.py
src/inqbus/ocf/generic/exits.py
src/inqbus/ocf/generic/handlers.py
src/inqbus/ocf/generic/parameter.py