Metadata-Version: 1.0
Name: inqbus.ocf.generic
Version: 0.1
Summary: Generic OCF resource agents
Home-page: http://inqbus.de
Author: volker jaenisch
Author-email: volker.jaenisch@inqbus.de
License: GPL
Download-URL: http://mypypi.inqbus.de/private/inqbus.ocf.generic
Keywords: pacemaker OCF resource agent HA
Platform: UNKNOWN
Classifier: Programming Language :: Python
Classifier: Environment :: Plugins
Classifier: Intended Audience :: System Administrators
Classifier: License :: Other/Proprietary License
Classifier: Natural Language :: English
Classifier: Operating System :: OS Independent
Classifier: Programming Language :: Python
